congruous.py
app/__init__.py
app/database.py
app/reports.py
app/assets/__init__.py
app/assets/fpdf.py
app/common/__init__.py
app/common/utils.py
congruous-0.1.6.dist-info/METADATA
congruous-0.1.6.dist-info/WHEEL
congruous-0.1.6.dist-info/entry_points.txt
congruous-0.1.6.dist-info/top_level.txt
congruous-0.1.6.dist-info/RECORD
