Metadata-Version: 2.1
Name: congruous
Version: 0.1.6
Summary: A python command-line tool to compare and generate accuracy reports for custom built OCR models.
Home-page: UNKNOWN
Author: Mahesh Kumaran T
Author-email: maheshtkumaran@gmail.com
License: UNKNOWN
Platform: UNKNOWN
Requires-Dist: Click
Requires-Dist: matplotlib
Requires-Dist: fuzzywuzzy[speedup]
Requires-Dist: tabulate
Requires-Dist: reportlab
Requires-Dist: pytz
